setup.cfg
setup.py
Very_SimpleXML.egg-info/PKG-INFO
Very_SimpleXML.egg-info/SOURCES.txt
Very_SimpleXML.egg-info/dependency_links.txt
Very_SimpleXML.egg-info/top_level.txt
simplexml/__init__.py
simplexml/core.py